google_takeout_parser/__init__.py
google_takeout_parser/__main__.py
google_takeout_parser/cache.py
google_takeout_parser/common.py
google_takeout_parser/http_allowlist.py
google_takeout_parser/log.py
google_takeout_parser/merge.py
google_takeout_parser/models.py
google_takeout_parser/parse_csv.py
google_takeout_parser/parse_json.py
google_takeout_parser/path_dispatch.py
google_takeout_parser/py.typed
google_takeout_parser/time_utils.py
google_takeout_parser/locales/__init__.py
google_takeout_parser/locales/all.py
google_takeout_parser/locales/common.py
google_takeout_parser/locales/de.py
google_takeout_parser/locales/en.py
google_takeout_parser/locales/main.py
google_takeout_parser/parse_html/__init__.py
google_takeout_parser/parse_html/activity.py
google_takeout_parser/parse_html/comment.py
google_takeout_parser/parse_html/html_time_utils.py
google_takeout_parser/parse_html/test_html_parsing.py
google_takeout_parser-0.1.13.dist-info/licenses/LICENSE
google_takeout_parser-0.1.13.dist-info/METADATA
google_takeout_parser-0.1.13.dist-info/WHEEL
google_takeout_parser-0.1.13.dist-info/entry_points.txt
google_takeout_parser-0.1.13.dist-info/top_level.txt
google_takeout_parser-0.1.13.dist-info/RECORD
