Metadata-Version: 2.4
Name: google_takeout_parser
Version: 0.1.13
Summary: Parses data out of your Google Takeout (History, Activity, Youtube, Locations, etc...)
Home-page: https://github.com/purarue/google_takeout_parser
Author: purarue
License: MIT
Keywords: google data parsing
Classifier: License :: OSI Approved :: MIT License
Classifier: Programming Language :: Python
Classifier: Programming Language :: Python :: 3
Classifier: Programming Language :: Python :: 3 :: Only
Classifier: Programming Language :: Python :: 3.9
Classifier: Programming Language :: Python :: 3.10
Classifier: Programming Language :: Python :: 3.11
Classifier: Programming Language :: Python :: 3.12
Classifier: Programming Language :: Python :: 3.13
Requires-Python: >=3.9
License-File: LICENSE
Requires-Dist: IPython
Requires-Dist: beautifulsoup4>=4.9.0
Requires-Dist: cachew>=0.16.20240129
Requires-Dist: click>=8.1
Requires-Dist: logzero>=1.7.0
Requires-Dist: lxml>=4.6.0
Requires-Dist: platformdirs>=2.3.0
Requires-Dist: pytz>=2021.3
Provides-Extra: optional
Requires-Dist: orjson; extra == "optional"
Provides-Extra: testing
Requires-Dist: flake8; extra == "testing"
Requires-Dist: mypy; extra == "testing"
Requires-Dist: pytest; extra == "testing"
Requires-Dist: types-beautifulsoup4; extra == "testing"
Requires-Dist: types-pytz; extra == "testing"
Dynamic: license-file
